setup.py
myBestTool.egg-info/PKG-INFO
myBestTool.egg-info/SOURCES.txt
myBestTool.egg-info/dependency_links.txt
myBestTool.egg-info/not-zip-safe
myBestTool.egg-info/requires.txt
myBestTool.egg-info/top_level.txt
tool/__init__.py
tool/myBestTool.py